{
    "le_setPos": "0",
    "le_setPos1": "-1500",
    "le_setPos2": "0",
    "le_setPos3": "1500",
    "cb_enable": true,
    "cb_mode": true,
    "radioButton": true,
    "le_pwm": "4095",
    "le_paP": "0.05",
    "le_paD": "0",
    "le_zeroShift": "0",
    "lineEdit": "Pos",
    "radioButton_2": true,
    "lineEdit_2": "Set Pos",
    "radioButton_3": false,
    "lineEdit_3": "Angle speed",
    "radioButton_4": false,
    "lineEdit_4": "Speed",
    "radioButton_5": false,
    "lineEdit_5": "Current",
    "le_speed": "9100",
    "cb_degrees": false,
    "sb_genAmpl": 10,
    "sb_genFreq": 3,
    "le_step": "0.5"
}